MANIFEST.in
README.md
setup.py
ffmpymedia/__init__.py
ffmpymedia/defs.py
ffmpymedia/media.py
ffmpymedia/parser.py
ffmpymedia/probe.py
ffmpymedia/transcoder.py
ffmpymedia.egg-info/PKG-INFO
ffmpymedia.egg-info/SOURCES.txt
ffmpymedia.egg-info/dependency_links.txt
ffmpymedia.egg-info/top_level.txt