Metadata-Version: 1.1
Name: ffmpymedia
Version: 0.3.2.2
Summary: Wrapper around the FFMPEG utility
Home-page: https://github.com/flaviocpontes/ffmpymedia
Author: Flávio Cardoso Pontes
Author-email: flaviopontes@acerp.org.br
License: MIT
Download-URL: https://github.com/flaviocpontes/ffmpymedia/tarball/0.3.2.2
Keywords: media,ffmpeg
Platform: UNKNOWN
Classifier: Development Status :: 4 - Beta
Classifier: Intended Audience :: Developers
Classifier: License :: OSI Approved :: MIT License
Classifier: Programming Language :: Python :: 3.3
Classifier: Programming Language :: Python :: 3.4
Classifier: Programming Language :: Python :: 3.5
